oobabot_plugin/__init__.py
oobabot_plugin/bootstrap.py
oobabot_plugin/button_enablers.py
oobabot_plugin/button_handlers.py
oobabot_plugin/controller.py
oobabot_plugin/input_handlers.py
oobabot_plugin/install.py
oobabot_plugin/instructions.md
oobabot_plugin/layout.py
oobabot_plugin/oobabot_log.css
oobabot_plugin/oobabot_log.js
oobabot_plugin/script.py
oobabot_plugin/server.py
oobabot_plugin/strings.py
oobabot_plugin/transcript.md
oobabot_plugin/transcript_view.py
oobabot_plugin/worker.py
oobabot_plugin-0.2.3.dist-info/LICENSE
oobabot_plugin-0.2.3.dist-info/METADATA
oobabot_plugin-0.2.3.dist-info/WHEEL
oobabot_plugin-0.2.3.dist-info/entry_points.txt
oobabot_plugin-0.2.3.dist-info/RECORD
