Metadata-Version: 2.1
Name: oobabot-plugin
Version: 0.2.3
Summary: A Discord bot plugin to oobabooga's text-generation-webui, based on oobabot.
Home-page: https://github.com/chrisrude/oobabot-plugin
License: MIT
Author: Christopher Rude
Author-email: chris@rudesoftware.net
Requires-Python: >=3.8.1,<4.0.0
Classifier: License :: OSI Approved :: MIT License
Classifier: Programming Language :: Python :: 3
Classifier: Programming Language :: Python :: 3.9
Classifier: Programming Language :: Python :: 3.10
Classifier: Programming Language :: Python :: 3.11
Requires-Dist: fastapi (>=0.99.1,<0.100.0)
Requires-Dist: gradio (>=3.33.1,<3.34.0)
Requires-Dist: gradio-client (==0.2.5)
Requires-Dist: oobabot (>=0.2.3,<0.3.0)
Project-URL: Repository, https://github.com/chrisrude/oobabot-plugin
